onlyaml/__init__.py
onlyaml/err.py
onlyaml/onlyaml.py
onlyaml/readonly_config.py
onlyaml-0.1.8.dist-info/LICENCE
onlyaml-0.1.8.dist-info/METADATA
onlyaml-0.1.8.dist-info/WHEEL
onlyaml-0.1.8.dist-info/top_level.txt
onlyaml-0.1.8.dist-info/RECORD
